alphaconf/__init__.py
alphaconf/interactive.py
alphaconf/invoke.py
alphaconf/logging_util.py
alphaconf/py.typed
alphaconf/internal/__init__.py
alphaconf/internal/arg_parser.py
alphaconf/internal/load_file.py
alphaconf/internal/type_resolvers.py
alphaconf-0.4.2.dist-info/LICENSE
alphaconf-0.4.2.dist-info/METADATA
alphaconf-0.4.2.dist-info/WHEEL
alphaconf-0.4.2.dist-info/top_level.txt
alphaconf-0.4.2.dist-info/RECORD
