Metadata-Version: 2.1
Name: alphaconf
Version: 0.4.2
Summary: Write simple scripts leveraging omegaconf
Author-email: Krzysztof Magusiak <chrmag@poczta.onet.pl>
License: BSD License
Project-URL: Homepage, https://github.com/kmagusiak/alphaconf
Keywords: configuration,omegaconf,script
Classifier: Programming Language :: Python :: 3
Classifier: Development Status :: 3 - Alpha
Classifier: License :: OSI Approved :: BSD License
Classifier: Environment :: Console
Requires-Python: >=3.8
License-File: LICENSE
Requires-Dist: omegaconf (>=2)
Provides-Extra: color
Requires-Dist: colorama ; extra == 'color'
Provides-Extra: dotenv
Requires-Dist: python-dotenv ; extra == 'dotenv'
Provides-Extra: invoke
Requires-Dist: invoke ; extra == 'invoke'
Provides-Extra: toml
Requires-Dist: toml ; extra == 'toml'
